Metadata-Version: 2.1
Name: suman-package
Version: 0.0.2
Summary: string upper concat
Home-page: UNKNOWN
Author: suman choudhary
License: UNKNOWN
Platform: UNKNOWN
Requires-Python: >=3.6
